{
  "todos": [
    {
      "id": 1,
      "task": "hey look",
      "toggle": "on"
    },
    {
      "task": "new look",
      "toggle": false,
      "id": 2
    },
    {
      "id": 3,
      "task": "new look 003",
      "toggle": false
    },
    {
      "task": "look look",
      "toggle": false,
      "id": 4
    },
    {
      "task": "hao ba",
      "toggle": false,
      "id": 5
    },
    {
      "id": 6,
      "task": "hehh0101",
      "toggle": "on"
    },
    {
      "task": "hehhe",
      "toggle": false,
      "id": 8
    },
    {
      "id": 9,
      "task": "xiix9999",
      "toggle": "on"
    },
    {
      "task": "kuku",
      "toggle": false,
      "id": 10
    },
    {
      "task": "really?111",
      "toggle": false,
      "id": 11
    },
    {
      "id": 12,
      "task": "assdhuhu",
      "toggle": "on"
    }
  ]
}